vscod/__init__.py
vscod/extensions_downloader.py
vscod/utils.py
vscod/vscode_downloader.py
vscod/scripts/__init__.py
vscod/scripts/vscod.py
vscod-0.1.0.dist-info/LICENSE.txt
vscod-0.1.0.dist-info/METADATA
vscod-0.1.0.dist-info/WHEEL
vscod-0.1.0.dist-info/entry_points.txt
vscod-0.1.0.dist-info/top_level.txt
vscod-0.1.0.dist-info/RECORD
