Metadata-Version: 2.1
Name: vscod
Version: 0.1.0
Summary: Download VSCode binaries and extensions offline.
Home-page: https://github.com/DivoK/vscod
Author: Divo Kaplan
Author-email: divokaplan@gmail.com
License: UNKNOWN
Keywords: vscode offline cli downloader tool
Platform: UNKNOWN
Classifier: Development Status :: 4 - Beta
Classifier: Environment :: Console
Classifier: License :: OSI Approved :: MIT License
Classifier: Operating System :: OS Independent
Classifier: Programming Language :: Python :: 3.7
Classifier: Programming Language :: Python :: 3.8
Classifier: Intended Audience :: Developers
Classifier: Intended Audience :: End Users/Desktop
Classifier: Intended Audience :: System Administrators
Classifier: Topic :: System :: Archiving :: Mirroring
Classifier: Topic :: Text Editors
Classifier: Topic :: Utilities
Requires-Python: >=3.7
Requires-Dist: loguru
Requires-Dist: aiohttp
Requires-Dist: aiofiles
Requires-Dist: cchardet
Requires-Dist: aiodns
Requires-Dist: click
